LICENSE.txt
MANIFEST.in
README.rst
setup.py
django_imperavi.egg-info/PKG-INFO
django_imperavi.egg-info/SOURCES.txt
django_imperavi.egg-info/dependency_links.txt
django_imperavi.egg-info/requires.txt
django_imperavi.egg-info/top_level.txt
imperavi/__init__.py
imperavi/__init__.pyc
imperavi/admin.py
imperavi/admin.pyc
imperavi/forms.py
imperavi/forms.pyc
imperavi/urls.py
imperavi/urls.pyc
imperavi/views.py
imperavi/views.pyc
imperavi/widget.py
imperavi/widget.pyc
imperavi/static/imperavi/jquery.js
imperavi/static/imperavi/redactor/.DS_Store
imperavi/static/imperavi/redactor/redactor.js
imperavi/static/imperavi/redactor/redactor.min.js
imperavi/static/imperavi/redactor/css/.DS_Store
imperavi/static/imperavi/redactor/css/docstyle.css
imperavi/static/imperavi/redactor/css/redactor.css
imperavi/static/imperavi/redactor/css/style.css
imperavi/static/imperavi/redactor/css/wym.css
imperavi/static/imperavi/redactor/img/icons.png
imperavi/static/imperavi/redactor/langs/bg.js
imperavi/static/imperavi/redactor/langs/by.js
imperavi/static/imperavi/redactor/langs/cs.js
imperavi/static/imperavi/redactor/langs/de.js
imperavi/static/imperavi/redactor/langs/en.js
imperavi/static/imperavi/redactor/langs/es.js
imperavi/static/imperavi/redactor/langs/fr.js
imperavi/static/imperavi/redactor/langs/hu.js
imperavi/static/imperavi/redactor/langs/it.js
imperavi/static/imperavi/redactor/langs/ja.js
imperavi/static/imperavi/redactor/langs/lv.js
imperavi/static/imperavi/redactor/langs/nl.js
imperavi/static/imperavi/redactor/langs/pl.js
imperavi/static/imperavi/redactor/langs/pt_br.js
imperavi/static/imperavi/redactor/langs/ru.js
imperavi/static/imperavi/redactor/langs/sq.js
imperavi/static/imperavi/redactor/langs/tr.js
imperavi/static/imperavi/redactor/langs/ua.js
imperavi/static/imperavi/redactor/langs/zh_cn.js
imperavi/static/imperavi/redactor/plugins/file.html
imperavi/static/imperavi/redactor/plugins/image.html
imperavi/static/imperavi/redactor/plugins/image_edit.html
imperavi/static/imperavi/redactor/plugins/link.html
imperavi/static/imperavi/redactor/plugins/table.html
imperavi/static/imperavi/redactor/plugins/video.html
imperavi/static/imperavi/redactor/toolbars/default.js
