Metadata-Version: 1.0
Name: django-imperavi
Version: 0.2.2
Summary: A django application that contains a class for admin interface to render a         text field as beautiful Imperavi WYSIWYG editor http://redactorjs.com/
Home-page: https://github.com/vasyabigi/django-imperavi
Author: Vasyl Stanislavchuk
Author-email: vasyl.stanislavchuk@gmail.com
License: MIT License
Keywords: django admin widget imperavi
Platform: any
